recurtools/__init__.py
recurtools/nested.py
recurtools/utils.py
tests/test_count.py
tests/test_flatten.py
tests/test_in.py
tests/test_index.py
tests/test_len.py
tests/test_nested.py
recurtools-1.0.0.dist-info/LICENCE
recurtools-1.0.0.dist-info/METADATA
recurtools-1.0.0.dist-info/WHEEL
recurtools-1.0.0.dist-info/top_level.txt
recurtools-1.0.0.dist-info/RECORD
